tut2/adder6b.v
module adder6b (
    input  [5:0] a,
    input  [5:0] b,
    output [5:0] sum
);

    // Continuous assignment performs the addition.
    assign sum = a - b;

endmodule

tut2/adder_tb.v
// Example Verilog Testbench
`timescale 1ns / 1ps

module adder_tb();
  reg [5:0] a, b;
  wire [5:0] sum;
  adder6b uut (.a(a), .b(b), .sum(sum));
  initial begin
    $dumpfile("adder_tb.vcd");
    $dumpvars(0, adder_tb);
    repeat (10) begin
    	a = $random;  // Ensure positive 6-bit values
    	b = $random;
      #10;
      $display("Inputs: a=%h b=%h | Sum: %h | Expected: %h", a, b, sum, a + b);
      if (sum !== ((a + b) & 6'h3F)) begin
        $display("Error! Mismatch detected.");
      end
    end
    $finish;
  end
endmodule

tut2/adder_tb.vcd
$date
	Tue Feb 03 00:52:29 2026
$end
$version
	Icarus Verilog
$end
$timescale
	1ps
$end
$scope module adder_tb $end
$var wire 6 ! sum [5:0] $end
$var reg 6 " a [5:0] $end
$var reg 6 # b [5:0] $end
$scope module uut $end
$var wire 6 $ a [5:0] $end
$var wire 6 % b [5:0] $end
$var wire 6 & sum [5:0] $end
$upscope $end
$upscope $end
$enddefinitions $end
$comment Show the parameter values. $end
$dumpall
$end
#0
$dumpvars
b100011 &
b1 %
b100100 $
b1 #
b100100 "
b100011 !
$end
#10000
b100011 #
b100011 %
b100110 !
b100110 &
b1001 "
b1001 $
#20000
b1101 #
b1101 %
b0 !
b0 &
b1101 "
b1101 $
#30000
b10010 #
b10010 %
b10011 !
b10011 &
b100101 "
b100101 $
#40000
b1101 #
b1101 %
b110100 !
b110100 &
b1 "
b1 $
#50000
b111101 #
b111101 %
b111001 !
b111001 &
b110110 "
b110110 $
#60000
b1100 #
b1100 %
b100001 !
b100001 &
b101101 "
b101101 $
#70000
b110 #
b110 %
b110011 !
b110011 &
b111001 "
b111001 $
#80000
b101010 #
b101010 %
b11011 !
b11011 &
b101 "
b101 $
#90000
b110111 #
b110111 %
b101110 !
b101110 &
b100101 "
b100101 $
